{
	"configurations" : 
	[
		{
			"directories" : 
			[
				{
					"build" : ".",
					"hasInstallRule" : true,
					"jsonFile" : "directory-.-Debug-991d5e4704f338fda7ab.json",
					"minimumCMakeVersion" : 
					{
						"string" : "3.5"
					},
					"projectIndex" : 0,
					"source" : ".",
					"targetIndexes" : 
					[
						0
					]
				}
			],
			"name" : "Debug",
			"projects" : 
			[
				{
					"directoryIndexes" : 
					[
						0
					],
					"name" : "2doParcial",
					"targetIndexes" : 
					[
						0
					]
				}
			],
			"targets" : 
			[
				{
					"directoryIndex" : 0,
					"id" : "2doParcial::@6890427a1f51a3e7e1df",
					"jsonFile" : "target-2doParcial-Debug-dc153e0111db0983c6f2.json",
					"name" : "2doParcial",
					"projectIndex" : 0
				}
			]
		}
	],
	"kind" : "codemodel",
	"paths" : 
	{
		"build" : "C:/Users/El_fi/OneDrive/Escritorio/Cpp/IFTS24/2doParcial/build-2doParcial-Desktop_Qt_6_4_0_MinGW_64_bit-Debug",
		"source" : "C:/Users/El_fi/OneDrive/Escritorio/Cpp/IFTS24/2doParcial/2doParcial"
	},
	"version" : 
	{
		"major" : 2,
		"minor" : 4
	}
}
